{"iteration": 97, "phase_idx": 0, "train_phase_idx": 0}
{"iteration": 194, "phase_idx": 1, "train_phase_idx": 1}
{"iteration": 291, "phase_idx": 2, "train_phase_idx": 2}
{"iteration": 388, "phase_idx": 3, "train_phase_idx": 3}
{"iteration": 485, "phase_idx": 4, "train_phase_idx": 4}
{"iteration": 582, "phase_idx": 5, "train_phase_idx": 5}
{"iteration": 679, "phase_idx": 6, "train_phase_idx": 6}
{"iteration": 776, "phase_idx": 7, "train_phase_idx": 7}
{"iteration": 873, "phase_idx": 8, "train_phase_idx": 8}
{"iteration": 970, "phase_idx": 9, "train_phase_idx": 9}
{"iteration": 1067, "phase_idx": 10, "train_phase_idx": 10}
{"iteration": 1164, "phase_idx": 11, "train_phase_idx": 11}
{"iteration": 1261, "phase_idx": 12, "train_phase_idx": 12}
{"iteration": 1358, "phase_idx": 13, "train_phase_idx": 13}
{"iteration": 1455, "phase_idx": 14, "train_phase_idx": 14}
{"iteration": 1552, "phase_idx": 15, "train_phase_idx": 15}
{"iteration": 1649, "phase_idx": 16, "train_phase_idx": 16}
{"iteration": 1746, "phase_idx": 17, "train_phase_idx": 17}
{"iteration": 1843, "phase_idx": 18, "train_phase_idx": 18}
{"iteration": 1940, "phase_idx": 19, "train_phase_idx": 19}
{"iteration": 2037, "phase_idx": 20, "train_phase_idx": 20}
{"iteration": 2134, "phase_idx": 21, "train_phase_idx": 21}
{"iteration": 2231, "phase_idx": 22, "train_phase_idx": 22}
{"iteration": 2328, "phase_idx": 23, "train_phase_idx": 23}
{"iteration": 2425, "phase_idx": 24, "train_phase_idx": 24}
{"iteration": 2522, "phase_idx": 25, "train_phase_idx": 25}
{"iteration": 2619, "phase_idx": 26, "train_phase_idx": 26}
{"iteration": 2716, "phase_idx": 27, "train_phase_idx": 27}
{"iteration": 2813, "phase_idx": 28, "train_phase_idx": 28}
{"iteration": 2910, "phase_idx": 29, "train_phase_idx": 29}
{"iteration": 3007, "phase_idx": 30, "train_phase_idx": 30}
{"iteration": 3104, "phase_idx": 31, "train_phase_idx": 31}
{"iteration": 3201, "phase_idx": 32, "train_phase_idx": 32}
{"iteration": 3298, "phase_idx": 33, "train_phase_idx": 33}
{"iteration": 3395, "phase_idx": 34, "train_phase_idx": 34}
{"iteration": 3492, "phase_idx": 35, "train_phase_idx": 35}
{"iteration": 3589, "phase_idx": 36, "train_phase_idx": 36}
{"iteration": 3686, "phase_idx": 37, "train_phase_idx": 37}
{"iteration": 3783, "phase_idx": 38, "train_phase_idx": 38}
{"iteration": 3880, "phase_idx": 39, "train_phase_idx": 39}
{"iteration": 3977, "phase_idx": 40, "train_phase_idx": 40}
{"iteration": 4074, "phase_idx": 41, "train_phase_idx": 41}
{"iteration": 4171, "phase_idx": 42, "train_phase_idx": 42}
{"iteration": 4268, "phase_idx": 43, "train_phase_idx": 43}
{"iteration": 4365, "phase_idx": 44, "train_phase_idx": 44}
{"iteration": 4462, "phase_idx": 45, "train_phase_idx": 45}
{"iteration": 4559, "phase_idx": 46, "train_phase_idx": 46}
{"iteration": 4656, "phase_idx": 47, "train_phase_idx": 47}
{"iteration": 4753, "phase_idx": 48, "train_phase_idx": 48}
{"iteration": 4850, "phase_idx": 49, "train_phase_idx": 49}
{"iteration": 4947, "phase_idx": 50, "train_phase_idx": 50}
{"iteration": 5044, "phase_idx": 51, "train_phase_idx": 51}
{"iteration": 5141, "phase_idx": 52, "train_phase_idx": 52}
{"iteration": 5238, "phase_idx": 53, "train_phase_idx": 53}
{"iteration": 5335, "phase_idx": 54, "train_phase_idx": 54}
{"iteration": 5432, "phase_idx": 55, "train_phase_idx": 55}
{"iteration": 5529, "phase_idx": 56, "train_phase_idx": 56}
{"iteration": 5626, "phase_idx": 57, "train_phase_idx": 57}
{"iteration": 5723, "phase_idx": 58, "train_phase_idx": 58}
{"iteration": 5820, "phase_idx": 59, "train_phase_idx": 59}
{"iteration": 5917, "phase_idx": 60, "train_phase_idx": 60}
{"iteration": 6014, "phase_idx": 61, "train_phase_idx": 61}
{"iteration": 6111, "phase_idx": 62, "train_phase_idx": 62}
{"iteration": 6208, "phase_idx": 63, "train_phase_idx": 63}
{"iteration": 6305, "phase_idx": 64, "train_phase_idx": 64}
{"iteration": 6402, "phase_idx": 65, "train_phase_idx": 65}
{"iteration": 6499, "phase_idx": 66, "train_phase_idx": 66}
{"iteration": 6596, "phase_idx": 67, "train_phase_idx": 67}
{"iteration": 6693, "phase_idx": 68, "train_phase_idx": 68}
{"iteration": 6790, "phase_idx": 69, "train_phase_idx": 69}
{"iteration": 6887, "phase_idx": 70, "train_phase_idx": 70}
{"iteration": 6984, "phase_idx": 71, "train_phase_idx": 71}
{"iteration": 7081, "phase_idx": 72, "train_phase_idx": 72}
{"iteration": 7178, "phase_idx": 73, "train_phase_idx": 73}
{"iteration": 7275, "phase_idx": 74, "train_phase_idx": 74}
{"iteration": 7372, "phase_idx": 75, "train_phase_idx": 75}
{"iteration": 7469, "phase_idx": 76, "train_phase_idx": 76}
{"iteration": 7566, "phase_idx": 77, "train_phase_idx": 77}
{"iteration": 7663, "phase_idx": 78, "train_phase_idx": 78}
{"iteration": 7760, "phase_idx": 79, "train_phase_idx": 79}
{"iteration": 7857, "phase_idx": 80, "train_phase_idx": 80}
{"iteration": 7954, "phase_idx": 81, "train_phase_idx": 81}
{"iteration": 8051, "phase_idx": 82, "train_phase_idx": 82}
{"iteration": 8148, "phase_idx": 83, "train_phase_idx": 83}
{"iteration": 8245, "phase_idx": 84, "train_phase_idx": 84}
{"iteration": 8342, "phase_idx": 85, "train_phase_idx": 85}
{"iteration": 8439, "phase_idx": 86, "train_phase_idx": 86}
{"iteration": 8536, "phase_idx": 87, "train_phase_idx": 87}
{"iteration": 8633, "phase_idx": 88, "train_phase_idx": 88}
{"iteration": 8730, "phase_idx": 89, "train_phase_idx": 89}
{"iteration": 8827, "phase_idx": 90, "train_phase_idx": 90}
{"iteration": 8924, "phase_idx": 91, "train_phase_idx": 91}
{"iteration": 9021, "phase_idx": 92, "train_phase_idx": 92}
{"iteration": 9118, "phase_idx": 93, "train_phase_idx": 93}
{"iteration": 9215, "phase_idx": 94, "train_phase_idx": 94}
{"iteration": 9312, "phase_idx": 95, "train_phase_idx": 95}
{"iteration": 9409, "phase_idx": 96, "train_phase_idx": 96}
{"iteration": 9506, "phase_idx": 97, "train_phase_idx": 97}
{"iteration": 9603, "phase_idx": 98, "train_phase_idx": 98}
{"iteration": 9700, "phase_idx": 99, "train_phase_idx": 99}
{"iteration": 9797, "phase_idx": 100, "train_phase_idx": 100}
{"iteration": 9894, "phase_idx": 101, "train_phase_idx": 101}
{"iteration": 9991, "phase_idx": 102, "train_phase_idx": 102}
{"iteration": 10088, "phase_idx": 103, "train_phase_idx": 103}
{"iteration": 10185, "phase_idx": 104, "train_phase_idx": 104}
{"iteration": 10282, "phase_idx": 105, "train_phase_idx": 105}
{"iteration": 10379, "phase_idx": 106, "train_phase_idx": 106}
{"iteration": 10476, "phase_idx": 107, "train_phase_idx": 107}
{"iteration": 10573, "phase_idx": 108, "train_phase_idx": 108}
{"iteration": 10670, "phase_idx": 109, "train_phase_idx": 109}
{"iteration": 10767, "phase_idx": 110, "train_phase_idx": 110}
{"iteration": 10864, "phase_idx": 111, "train_phase_idx": 111}
{"iteration": 10961, "phase_idx": 112, "train_phase_idx": 112}
{"iteration": 11058, "phase_idx": 113, "train_phase_idx": 113}
{"iteration": 11155, "phase_idx": 114, "train_phase_idx": 114}
{"iteration": 11252, "phase_idx": 115, "train_phase_idx": 115}
{"iteration": 11349, "phase_idx": 116, "train_phase_idx": 116}
{"iteration": 11446, "phase_idx": 117, "train_phase_idx": 117}
{"iteration": 11543, "phase_idx": 118, "train_phase_idx": 118}
{"iteration": 11640, "phase_idx": 119, "train_phase_idx": 119}
{"iteration": 11737, "phase_idx": 120, "train_phase_idx": 120}
{"iteration": 11834, "phase_idx": 121, "train_phase_idx": 121}
{"iteration": 11931, "phase_idx": 122, "train_phase_idx": 122}
{"iteration": 12028, "phase_idx": 123, "train_phase_idx": 123}
{"iteration": 12125, "phase_idx": 124, "train_phase_idx": 124}
{"iteration": 12222, "phase_idx": 125, "train_phase_idx": 125}
{"iteration": 12319, "phase_idx": 126, "train_phase_idx": 126}
{"iteration": 12416, "phase_idx": 127, "train_phase_idx": 127}
{"iteration": 12513, "phase_idx": 128, "train_phase_idx": 128}
{"iteration": 12610, "phase_idx": 129, "train_phase_idx": 129}
{"iteration": 12707, "phase_idx": 130, "train_phase_idx": 130}
{"iteration": 12804, "phase_idx": 131, "train_phase_idx": 131}
{"iteration": 12901, "phase_idx": 132, "train_phase_idx": 132}
{"iteration": 12998, "phase_idx": 133, "train_phase_idx": 133}
{"iteration": 13095, "phase_idx": 134, "train_phase_idx": 134}
{"iteration": 13192, "phase_idx": 135, "train_phase_idx": 135}
{"iteration": 13289, "phase_idx": 136, "train_phase_idx": 136}
{"iteration": 13386, "phase_idx": 137, "train_phase_idx": 137}
{"iteration": 13483, "phase_idx": 138, "train_phase_idx": 138}
{"iteration": 13580, "phase_idx": 139, "train_phase_idx": 139}
{"iteration": 13677, "phase_idx": 140, "train_phase_idx": 140}
{"iteration": 13774, "phase_idx": 141, "train_phase_idx": 141}
{"iteration": 13871, "phase_idx": 142, "train_phase_idx": 142}
{"iteration": 13968, "phase_idx": 143, "train_phase_idx": 143}
{"iteration": 14065, "phase_idx": 144, "train_phase_idx": 144}
{"iteration": 14162, "phase_idx": 145, "train_phase_idx": 145}
{"iteration": 14259, "phase_idx": 146, "train_phase_idx": 146}
{"iteration": 14356, "phase_idx": 147, "train_phase_idx": 147}
{"iteration": 14453, "phase_idx": 148, "train_phase_idx": 148}
{"iteration": 14550, "phase_idx": 149, "train_phase_idx": 149}
{"iteration": 14647, "phase_idx": 150, "train_phase_idx": 150}
{"iteration": 14744, "phase_idx": 151, "train_phase_idx": 151}
{"iteration": 14841, "phase_idx": 152, "train_phase_idx": 152}
{"iteration": 14938, "phase_idx": 153, "train_phase_idx": 153}
{"iteration": 15035, "phase_idx": 154, "train_phase_idx": 154}
{"iteration": 15132, "phase_idx": 155, "train_phase_idx": 155}
{"iteration": 15229, "phase_idx": 156, "train_phase_idx": 156}
{"iteration": 15326, "phase_idx": 157, "train_phase_idx": 157}
{"iteration": 15423, "phase_idx": 158, "train_phase_idx": 158}
{"iteration": 15520, "phase_idx": 159, "train_phase_idx": 159}
{"iteration": 15617, "phase_idx": 160, "train_phase_idx": 160}
{"iteration": 15714, "phase_idx": 161, "train_phase_idx": 161}
{"iteration": 15811, "phase_idx": 162, "train_phase_idx": 162}
{"iteration": 15908, "phase_idx": 163, "train_phase_idx": 163}
{"iteration": 16005, "phase_idx": 164, "train_phase_idx": 164}
{"iteration": 16102, "phase_idx": 165, "train_phase_idx": 165}
{"iteration": 16199, "phase_idx": 166, "train_phase_idx": 166}
{"iteration": 16296, "phase_idx": 167, "train_phase_idx": 167}
{"iteration": 16393, "phase_idx": 168, "train_phase_idx": 168}
{"iteration": 16490, "phase_idx": 169, "train_phase_idx": 169}
{"iteration": 16587, "phase_idx": 170, "train_phase_idx": 170}
{"iteration": 16684, "phase_idx": 171, "train_phase_idx": 171}
{"iteration": 16781, "phase_idx": 172, "train_phase_idx": 172}
{"iteration": 16878, "phase_idx": 173, "train_phase_idx": 173}
{"iteration": 16975, "phase_idx": 174, "train_phase_idx": 174}
{"iteration": 17072, "phase_idx": 175, "train_phase_idx": 175}
{"iteration": 17169, "phase_idx": 176, "train_phase_idx": 176}
{"iteration": 17266, "phase_idx": 177, "train_phase_idx": 177}
{"iteration": 17363, "phase_idx": 178, "train_phase_idx": 178}
{"iteration": 17460, "phase_idx": 179, "train_phase_idx": 179}
{"iteration": 17557, "phase_idx": 180, "train_phase_idx": 180}
{"iteration": 17654, "phase_idx": 181, "train_phase_idx": 181}
{"iteration": 17751, "phase_idx": 182, "train_phase_idx": 182}
{"iteration": 17848, "phase_idx": 183, "train_phase_idx": 183}
{"iteration": 17945, "phase_idx": 184, "train_phase_idx": 184}
{"iteration": 18042, "phase_idx": 185, "train_phase_idx": 185}
{"iteration": 18139, "phase_idx": 186, "train_phase_idx": 186}
{"iteration": 18236, "phase_idx": 187, "train_phase_idx": 187}
{"iteration": 18333, "phase_idx": 188, "train_phase_idx": 188}
{"iteration": 18430, "phase_idx": 189, "train_phase_idx": 189}
{"iteration": 18527, "phase_idx": 190, "train_phase_idx": 190}
{"iteration": 18624, "phase_idx": 191, "train_phase_idx": 191}
{"iteration": 18721, "phase_idx": 192, "train_phase_idx": 192}
{"iteration": 18818, "phase_idx": 193, "train_phase_idx": 193}
{"iteration": 18915, "phase_idx": 194, "train_phase_idx": 194}
{"iteration": 19012, "phase_idx": 195, "train_phase_idx": 195}
{"iteration": 19109, "phase_idx": 196, "train_phase_idx": 196}
{"iteration": 19206, "phase_idx": 197, "train_phase_idx": 197}
{"iteration": 19303, "phase_idx": 198, "train_phase_idx": 198}
{"iteration": 19400, "phase_idx": 199, "train_phase_idx": 199}
{"iteration": 19497, "phase_idx": 200, "train_phase_idx": 200}
{"iteration": 19594, "phase_idx": 201, "train_phase_idx": 201}
{"iteration": 19691, "phase_idx": 202, "train_phase_idx": 202}
{"iteration": 19788, "phase_idx": 203, "train_phase_idx": 203}
{"iteration": 19885, "phase_idx": 204, "train_phase_idx": 204}
{"iteration": 19982, "phase_idx": 205, "train_phase_idx": 205}
{"iteration": 20079, "phase_idx": 206, "train_phase_idx": 206}
{"iteration": 20176, "phase_idx": 207, "train_phase_idx": 207}
{"iteration": 20273, "phase_idx": 208, "train_phase_idx": 208}
{"iteration": 20370, "phase_idx": 209, "train_phase_idx": 209}
{"iteration": 20467, "phase_idx": 210, "train_phase_idx": 210}
{"iteration": 20564, "phase_idx": 211, "train_phase_idx": 211}
{"iteration": 20661, "phase_idx": 212, "train_phase_idx": 212}
{"iteration": 20758, "phase_idx": 213, "train_phase_idx": 213}
{"iteration": 20855, "phase_idx": 214, "train_phase_idx": 214}
{"iteration": 20952, "phase_idx": 215, "train_phase_idx": 215}
{"iteration": 21049, "phase_idx": 216, "train_phase_idx": 216}
{"iteration": 21146, "phase_idx": 217, "train_phase_idx": 217}
{"iteration": 21243, "phase_idx": 218, "train_phase_idx": 218}
{"iteration": 21340, "phase_idx": 219, "train_phase_idx": 219}
{"iteration": 21437, "phase_idx": 220, "train_phase_idx": 220}
{"iteration": 21534, "phase_idx": 221, "train_phase_idx": 221}
{"iteration": 21631, "phase_idx": 222, "train_phase_idx": 222}
{"iteration": 21728, "phase_idx": 223, "train_phase_idx": 223}
{"iteration": 21825, "phase_idx": 224, "train_phase_idx": 224}
{"iteration": 21922, "phase_idx": 225, "train_phase_idx": 225}
{"iteration": 22019, "phase_idx": 226, "train_phase_idx": 226}
{"iteration": 22116, "phase_idx": 227, "train_phase_idx": 227}
{"iteration": 22213, "phase_idx": 228, "train_phase_idx": 228}
{"iteration": 22310, "phase_idx": 229, "train_phase_idx": 229}
{"iteration": 22407, "phase_idx": 230, "train_phase_idx": 230}
{"iteration": 22504, "phase_idx": 231, "train_phase_idx": 231}
{"iteration": 22601, "phase_idx": 232, "train_phase_idx": 232}
{"iteration": 22698, "phase_idx": 233, "train_phase_idx": 233}
{"iteration": 22795, "phase_idx": 234, "train_phase_idx": 234}
{"iteration": 22892, "phase_idx": 235, "train_phase_idx": 235}
{"iteration": 22989, "phase_idx": 236, "train_phase_idx": 236}
{"iteration": 23086, "phase_idx": 237, "train_phase_idx": 237}
{"iteration": 23183, "phase_idx": 238, "train_phase_idx": 238}
{"iteration": 23280, "phase_idx": 239, "train_phase_idx": 239}
{"iteration": 23377, "phase_idx": 240, "train_phase_idx": 240}
{"iteration": 23474, "phase_idx": 241, "train_phase_idx": 241}
{"iteration": 23571, "phase_idx": 242, "train_phase_idx": 242}
{"iteration": 23668, "phase_idx": 243, "train_phase_idx": 243}
{"iteration": 23765, "phase_idx": 244, "train_phase_idx": 244}
{"iteration": 23862, "phase_idx": 245, "train_phase_idx": 245}
{"iteration": 23959, "phase_idx": 246, "train_phase_idx": 246}
{"iteration": 24056, "phase_idx": 247, "train_phase_idx": 247}
{"iteration": 24153, "phase_idx": 248, "train_phase_idx": 248}
{"iteration": 24250, "phase_idx": 249, "train_phase_idx": 249}
{"iteration": 24347, "phase_idx": 250, "train_phase_idx": 250}
{"iteration": 24444, "phase_idx": 251, "train_phase_idx": 251}
{"iteration": 24541, "phase_idx": 252, "train_phase_idx": 252}
{"iteration": 24638, "phase_idx": 253, "train_phase_idx": 253}
{"iteration": 24735, "phase_idx": 254, "train_phase_idx": 254}
{"iteration": 24832, "phase_idx": 255, "train_phase_idx": 255}
{"iteration": 24929, "phase_idx": 256, "train_phase_idx": 256}
{"iteration": 25026, "phase_idx": 257, "train_phase_idx": 257}
{"iteration": 25123, "phase_idx": 258, "train_phase_idx": 258}
{"iteration": 25220, "phase_idx": 259, "train_phase_idx": 259}
{"iteration": 25317, "phase_idx": 260, "train_phase_idx": 260}
{"iteration": 25414, "phase_idx": 261, "train_phase_idx": 261}
{"iteration": 25511, "phase_idx": 262, "train_phase_idx": 262}
{"iteration": 25608, "phase_idx": 263, "train_phase_idx": 263}
{"iteration": 25705, "phase_idx": 264, "train_phase_idx": 264}
{"iteration": 25802, "phase_idx": 265, "train_phase_idx": 265}
{"iteration": 25899, "phase_idx": 266, "train_phase_idx": 266}
{"iteration": 25996, "phase_idx": 267, "train_phase_idx": 267}
{"iteration": 26093, "phase_idx": 268, "train_phase_idx": 268}
{"iteration": 26190, "phase_idx": 269, "train_phase_idx": 269}
{"iteration": 26287, "phase_idx": 270, "train_phase_idx": 270}
{"iteration": 26384, "phase_idx": 271, "train_phase_idx": 271}
{"iteration": 26481, "phase_idx": 272, "train_phase_idx": 272}
{"iteration": 26578, "phase_idx": 273, "train_phase_idx": 273}
{"iteration": 26675, "phase_idx": 274, "train_phase_idx": 274}
{"iteration": 26772, "phase_idx": 275, "train_phase_idx": 275}
{"iteration": 26869, "phase_idx": 276, "train_phase_idx": 276}
{"iteration": 26966, "phase_idx": 277, "train_phase_idx": 277}
{"iteration": 27063, "phase_idx": 278, "train_phase_idx": 278}
{"iteration": 27160, "phase_idx": 279, "train_phase_idx": 279}
{"iteration": 27257, "phase_idx": 280, "train_phase_idx": 280}
{"iteration": 27354, "phase_idx": 281, "train_phase_idx": 281}
{"iteration": 27451, "phase_idx": 282, "train_phase_idx": 282}
{"iteration": 27548, "phase_idx": 283, "train_phase_idx": 283}
{"iteration": 27645, "phase_idx": 284, "train_phase_idx": 284}
{"iteration": 27742, "phase_idx": 285, "train_phase_idx": 285}
{"iteration": 27839, "phase_idx": 286, "train_phase_idx": 286}
{"iteration": 27936, "phase_idx": 287, "train_phase_idx": 287}
{"iteration": 28033, "phase_idx": 288, "train_phase_idx": 288}
{"iteration": 28130, "phase_idx": 289, "train_phase_idx": 289}
{"iteration": 28227, "phase_idx": 290, "train_phase_idx": 290}
{"iteration": 28324, "phase_idx": 291, "train_phase_idx": 291}
{"iteration": 28421, "phase_idx": 292, "train_phase_idx": 292}
{"iteration": 28518, "phase_idx": 293, "train_phase_idx": 293}
{"iteration": 28615, "phase_idx": 294, "train_phase_idx": 294}
{"iteration": 28712, "phase_idx": 295, "train_phase_idx": 295}
{"iteration": 28809, "phase_idx": 296, "train_phase_idx": 296}
{"iteration": 28906, "phase_idx": 297, "train_phase_idx": 297}
{"iteration": 29003, "phase_idx": 298, "train_phase_idx": 298}
{"iteration": 29100, "phase_idx": 299, "train_phase_idx": 299}
{"iteration": 29197, "phase_idx": 300, "train_phase_idx": 300}
{"iteration": 29294, "phase_idx": 301, "train_phase_idx": 301}
{"iteration": 29391, "phase_idx": 302, "train_phase_idx": 302}
{"iteration": 29488, "phase_idx": 303, "train_phase_idx": 303}
{"iteration": 29585, "phase_idx": 304, "train_phase_idx": 304}
{"iteration": 29682, "phase_idx": 305, "train_phase_idx": 305}
{"iteration": 29779, "phase_idx": 306, "train_phase_idx": 306}
{"iteration": 29876, "phase_idx": 307, "train_phase_idx": 307}
{"iteration": 29973, "phase_idx": 308, "train_phase_idx": 308}
{"iteration": 30070, "phase_idx": 309, "train_phase_idx": 309}
{"iteration": 30167, "phase_idx": 310, "train_phase_idx": 310}
{"iteration": 30264, "phase_idx": 311, "train_phase_idx": 311}
{"iteration": 30361, "phase_idx": 312, "train_phase_idx": 312}
{"iteration": 30458, "phase_idx": 313, "train_phase_idx": 313}
{"iteration": 30555, "phase_idx": 314, "train_phase_idx": 314}
{"iteration": 30652, "phase_idx": 315, "train_phase_idx": 315}
{"iteration": 30749, "phase_idx": 316, "train_phase_idx": 316}
{"iteration": 30846, "phase_idx": 317, "train_phase_idx": 317}
{"iteration": 30943, "phase_idx": 318, "train_phase_idx": 318}
{"iteration": 31040, "phase_idx": 319, "train_phase_idx": 319}
{"iteration": 31137, "phase_idx": 320, "train_phase_idx": 320}
{"iteration": 31234, "phase_idx": 321, "train_phase_idx": 321}
{"iteration": 31331, "phase_idx": 322, "train_phase_idx": 322}
{"iteration": 31428, "phase_idx": 323, "train_phase_idx": 323}
{"iteration": 31525, "phase_idx": 324, "train_phase_idx": 324}
{"iteration": 31622, "phase_idx": 325, "train_phase_idx": 325}
{"iteration": 31719, "phase_idx": 326, "train_phase_idx": 326}
{"iteration": 31816, "phase_idx": 327, "train_phase_idx": 327}
{"iteration": 31913, "phase_idx": 328, "train_phase_idx": 328}
{"iteration": 32010, "phase_idx": 329, "train_phase_idx": 329}
{"iteration": 32107, "phase_idx": 330, "train_phase_idx": 330}
{"iteration": 32204, "phase_idx": 331, "train_phase_idx": 331}
{"iteration": 32301, "phase_idx": 332, "train_phase_idx": 332}
{"iteration": 32398, "phase_idx": 333, "train_phase_idx": 333}
{"iteration": 32495, "phase_idx": 334, "train_phase_idx": 334}
{"iteration": 32592, "phase_idx": 335, "train_phase_idx": 335}
{"iteration": 32689, "phase_idx": 336, "train_phase_idx": 336}
{"iteration": 32786, "phase_idx": 337, "train_phase_idx": 337}
{"iteration": 32883, "phase_idx": 338, "train_phase_idx": 338}
{"iteration": 32980, "phase_idx": 339, "train_phase_idx": 339}
{"iteration": 33077, "phase_idx": 340, "train_phase_idx": 340}
{"iteration": 33174, "phase_idx": 341, "train_phase_idx": 341}
{"iteration": 33271, "phase_idx": 342, "train_phase_idx": 342}
{"iteration": 33368, "phase_idx": 343, "train_phase_idx": 343}
{"iteration": 33465, "phase_idx": 344, "train_phase_idx": 344}
{"iteration": 33562, "phase_idx": 345, "train_phase_idx": 345}
{"iteration": 33659, "phase_idx": 346, "train_phase_idx": 346}
{"iteration": 33756, "phase_idx": 347, "train_phase_idx": 347}
{"iteration": 33853, "phase_idx": 348, "train_phase_idx": 348}
{"iteration": 33950, "phase_idx": 349, "train_phase_idx": 349}
{"iteration": 34047, "phase_idx": 350, "train_phase_idx": 350}
{"iteration": 34144, "phase_idx": 351, "train_phase_idx": 351}
{"iteration": 34241, "phase_idx": 352, "train_phase_idx": 352}
{"iteration": 34338, "phase_idx": 353, "train_phase_idx": 353}
{"iteration": 34435, "phase_idx": 354, "train_phase_idx": 354}
{"iteration": 34532, "phase_idx": 355, "train_phase_idx": 355}
{"iteration": 34629, "phase_idx": 356, "train_phase_idx": 356}
{"iteration": 34726, "phase_idx": 357, "train_phase_idx": 357}
{"iteration": 34823, "phase_idx": 358, "train_phase_idx": 358}
{"iteration": 34920, "phase_idx": 359, "train_phase_idx": 359}
{"iteration": 35017, "phase_idx": 360, "train_phase_idx": 360}
{"iteration": 35114, "phase_idx": 361, "train_phase_idx": 361}
{"iteration": 35211, "phase_idx": 362, "train_phase_idx": 362}
{"iteration": 35308, "phase_idx": 363, "train_phase_idx": 363}
{"iteration": 35405, "phase_idx": 364, "train_phase_idx": 364}
{"iteration": 35502, "phase_idx": 365, "train_phase_idx": 365}
{"iteration": 35599, "phase_idx": 366, "train_phase_idx": 366}
{"iteration": 35696, "phase_idx": 367, "train_phase_idx": 367}
{"iteration": 35793, "phase_idx": 368, "train_phase_idx": 368}
{"iteration": 35890, "phase_idx": 369, "train_phase_idx": 369}
{"iteration": 35987, "phase_idx": 370, "train_phase_idx": 370}
{"iteration": 36084, "phase_idx": 371, "train_phase_idx": 371}
{"iteration": 36181, "phase_idx": 372, "train_phase_idx": 372}
{"iteration": 36278, "phase_idx": 373, "train_phase_idx": 373}
{"iteration": 36375, "phase_idx": 374, "train_phase_idx": 374}
{"iteration": 36472, "phase_idx": 375, "train_phase_idx": 375}
{"iteration": 36569, "phase_idx": 376, "train_phase_idx": 376}
{"iteration": 36666, "phase_idx": 377, "train_phase_idx": 377}
{"iteration": 36763, "phase_idx": 378, "train_phase_idx": 378}
{"iteration": 36860, "phase_idx": 379, "train_phase_idx": 379}
{"iteration": 36957, "phase_idx": 380, "train_phase_idx": 380}
{"iteration": 37054, "phase_idx": 381, "train_phase_idx": 381}
{"iteration": 37151, "phase_idx": 382, "train_phase_idx": 382}
{"iteration": 37248, "phase_idx": 383, "train_phase_idx": 383}
{"iteration": 37345, "phase_idx": 384, "train_phase_idx": 384}
{"iteration": 37442, "phase_idx": 385, "train_phase_idx": 385}
{"iteration": 37539, "phase_idx": 386, "train_phase_idx": 386}
{"iteration": 37636, "phase_idx": 387, "train_phase_idx": 387}
{"iteration": 37733, "phase_idx": 388, "train_phase_idx": 388}
{"iteration": 37830, "phase_idx": 389, "train_phase_idx": 389}
{"iteration": 37927, "phase_idx": 390, "train_phase_idx": 390}
{"iteration": 38024, "phase_idx": 391, "train_phase_idx": 391}
{"iteration": 38121, "phase_idx": 392, "train_phase_idx": 392}
{"iteration": 38218, "phase_idx": 393, "train_phase_idx": 393}
{"iteration": 38315, "phase_idx": 394, "train_phase_idx": 394}
{"iteration": 38412, "phase_idx": 395, "train_phase_idx": 395}
{"iteration": 38509, "phase_idx": 396, "train_phase_idx": 396}
{"iteration": 38606, "phase_idx": 397, "train_phase_idx": 397}
{"iteration": 38703, "phase_idx": 398, "train_phase_idx": 398}
{"iteration": 38800, "phase_idx": 399, "train_phase_idx": 399}
{"iteration": 38897, "phase_idx": 400, "train_phase_idx": 400}
{"iteration": 38994, "phase_idx": 401, "train_phase_idx": 401}
{"iteration": 39091, "phase_idx": 402, "train_phase_idx": 402}
{"iteration": 39188, "phase_idx": 403, "train_phase_idx": 403}
{"iteration": 39285, "phase_idx": 404, "train_phase_idx": 404}
{"iteration": 39382, "phase_idx": 405, "train_phase_idx": 405}
{"iteration": 39479, "phase_idx": 406, "train_phase_idx": 406}
{"iteration": 39576, "phase_idx": 407, "train_phase_idx": 407}
{"iteration": 39673, "phase_idx": 408, "train_phase_idx": 408}
{"iteration": 39770, "phase_idx": 409, "train_phase_idx": 409}
{"iteration": 39867, "phase_idx": 410, "train_phase_idx": 410}
{"iteration": 39964, "phase_idx": 411, "train_phase_idx": 411}
{"iteration": 40061, "phase_idx": 412, "train_phase_idx": 412}
{"iteration": 40158, "phase_idx": 413, "train_phase_idx": 413}
{"iteration": 40255, "phase_idx": 414, "train_phase_idx": 414}
{"iteration": 40352, "phase_idx": 415, "train_phase_idx": 415}
{"iteration": 40449, "phase_idx": 416, "train_phase_idx": 416}
{"iteration": 40546, "phase_idx": 417, "train_phase_idx": 417}
{"iteration": 40643, "phase_idx": 418, "train_phase_idx": 418}
{"iteration": 40740, "phase_idx": 419, "train_phase_idx": 419}
{"iteration": 40837, "phase_idx": 420, "train_phase_idx": 420}
{"iteration": 40934, "phase_idx": 421, "train_phase_idx": 421}
{"iteration": 41031, "phase_idx": 422, "train_phase_idx": 422}
{"iteration": 41128, "phase_idx": 423, "train_phase_idx": 423}
{"iteration": 41225, "phase_idx": 424, "train_phase_idx": 424}
{"iteration": 41322, "phase_idx": 425, "train_phase_idx": 425}
{"iteration": 41419, "phase_idx": 426, "train_phase_idx": 426}
{"iteration": 41516, "phase_idx": 427, "train_phase_idx": 427}
{"iteration": 41613, "phase_idx": 428, "train_phase_idx": 428}
{"iteration": 41710, "phase_idx": 429, "train_phase_idx": 429}
{"iteration": 41807, "phase_idx": 430, "train_phase_idx": 430}
{"iteration": 41904, "phase_idx": 431, "train_phase_idx": 431}
{"iteration": 42001, "phase_idx": 432, "train_phase_idx": 432}
{"iteration": 42098, "phase_idx": 433, "train_phase_idx": 433}
{"iteration": 42195, "phase_idx": 434, "train_phase_idx": 434}
{"iteration": 42292, "phase_idx": 435, "train_phase_idx": 435}
{"iteration": 42389, "phase_idx": 436, "train_phase_idx": 436}
{"iteration": 42486, "phase_idx": 437, "train_phase_idx": 437}
{"iteration": 42583, "phase_idx": 438, "train_phase_idx": 438}
{"iteration": 42680, "phase_idx": 439, "train_phase_idx": 439}
{"iteration": 42777, "phase_idx": 440, "train_phase_idx": 440}
{"iteration": 42874, "phase_idx": 441, "train_phase_idx": 441}
{"iteration": 42971, "phase_idx": 442, "train_phase_idx": 442}
{"iteration": 43068, "phase_idx": 443, "train_phase_idx": 443}
{"iteration": 43165, "phase_idx": 444, "train_phase_idx": 444}
{"iteration": 43262, "phase_idx": 445, "train_phase_idx": 445}
{"iteration": 43359, "phase_idx": 446, "train_phase_idx": 446}
{"iteration": 43456, "phase_idx": 447, "train_phase_idx": 447}
{"iteration": 43553, "phase_idx": 448, "train_phase_idx": 448}
{"iteration": 43650, "phase_idx": 449, "train_phase_idx": 449}
{"iteration": 43747, "phase_idx": 450, "train_phase_idx": 450}
{"iteration": 43844, "phase_idx": 451, "train_phase_idx": 451}
{"iteration": 43941, "phase_idx": 452, "train_phase_idx": 452}
{"iteration": 44038, "phase_idx": 453, "train_phase_idx": 453}
{"iteration": 44135, "phase_idx": 454, "train_phase_idx": 454}
{"iteration": 44232, "phase_idx": 455, "train_phase_idx": 455}
{"iteration": 44329, "phase_idx": 456, "train_phase_idx": 456}
{"iteration": 44426, "phase_idx": 457, "train_phase_idx": 457}
{"iteration": 44523, "phase_idx": 458, "train_phase_idx": 458}
{"iteration": 44620, "phase_idx": 459, "train_phase_idx": 459}
{"iteration": 44717, "phase_idx": 460, "train_phase_idx": 460}
{"iteration": 44814, "phase_idx": 461, "train_phase_idx": 461}
{"iteration": 44911, "phase_idx": 462, "train_phase_idx": 462}
{"iteration": 45008, "phase_idx": 463, "train_phase_idx": 463}
{"iteration": 45105, "phase_idx": 464, "train_phase_idx": 464}
{"iteration": 45202, "phase_idx": 465, "train_phase_idx": 465}
{"iteration": 45299, "phase_idx": 466, "train_phase_idx": 466}
{"iteration": 45396, "phase_idx": 467, "train_phase_idx": 467}
{"iteration": 45493, "phase_idx": 468, "train_phase_idx": 468}
{"iteration": 45590, "phase_idx": 469, "train_phase_idx": 469}
{"iteration": 45687, "phase_idx": 470, "train_phase_idx": 470}
{"iteration": 45784, "phase_idx": 471, "train_phase_idx": 471}
{"iteration": 45881, "phase_idx": 472, "train_phase_idx": 472}
{"iteration": 45978, "phase_idx": 473, "train_phase_idx": 473}
{"iteration": 46075, "phase_idx": 474, "train_phase_idx": 474}
{"iteration": 46172, "phase_idx": 475, "train_phase_idx": 475}
{"iteration": 46269, "phase_idx": 476, "train_phase_idx": 476}
{"iteration": 46366, "phase_idx": 477, "train_phase_idx": 477}
{"iteration": 46463, "phase_idx": 478, "train_phase_idx": 478}
{"iteration": 46560, "phase_idx": 479, "train_phase_idx": 479}
{"iteration": 46657, "phase_idx": 480, "train_phase_idx": 480}
{"iteration": 46754, "phase_idx": 481, "train_phase_idx": 481}
{"iteration": 46851, "phase_idx": 482, "train_phase_idx": 482}
{"iteration": 46948, "phase_idx": 483, "train_phase_idx": 483}
{"iteration": 46754, "phase_idx": 481, "train_phase_idx": 481}
{"iteration": 46851, "phase_idx": 482, "train_phase_idx": 482}
{"iteration": 46948, "phase_idx": 483, "train_phase_idx": 483}
{"iteration": 47045, "phase_idx": 484, "train_phase_idx": 484}
{"iteration": 47142, "phase_idx": 485, "train_phase_idx": 485}
{"iteration": 47239, "phase_idx": 486, "train_phase_idx": 486}
{"iteration": 47336, "phase_idx": 487, "train_phase_idx": 487}
{"iteration": 47433, "phase_idx": 488, "train_phase_idx": 488}
{"iteration": 47530, "phase_idx": 489, "train_phase_idx": 489}
{"iteration": 47627, "phase_idx": 490, "train_phase_idx": 490}
{"iteration": 47724, "phase_idx": 491, "train_phase_idx": 491}
{"iteration": 47821, "phase_idx": 492, "train_phase_idx": 492}
{"iteration": 47918, "phase_idx": 493, "train_phase_idx": 493}
{"iteration": 48015, "phase_idx": 494, "train_phase_idx": 494}
{"iteration": 48112, "phase_idx": 495, "train_phase_idx": 495}
{"iteration": 48209, "phase_idx": 496, "train_phase_idx": 496}
{"iteration": 48306, "phase_idx": 497, "train_phase_idx": 497}
{"iteration": 48403, "phase_idx": 498, "train_phase_idx": 498}
{"iteration": 48500, "phase_idx": 499, "train_phase_idx": 499}
